main.py
setup.py
BaibitMF.egg-info/PKG-INFO
BaibitMF.egg-info/SOURCES.txt
BaibitMF.egg-info/dependency_links.txt
BaibitMF.egg-info/requires.txt
BaibitMF.egg-info/top_level.txt